odoo10_addon_website_snippet_barcode-10.0.1.0.0-py2.7-nspkg.pth
odoo/addons/website_snippet_barcode/README.rst
odoo/addons/website_snippet_barcode/__init__.py
odoo/addons/website_snippet_barcode/__manifest__.py
odoo/addons/website_snippet_barcode/demo/assets_demo.xml
odoo/addons/website_snippet_barcode/demo/website_snippet_barcode_demo.xml
odoo/addons/website_snippet_barcode/static/description/icon.png
odoo/addons/website_snippet_barcode/static/description/icon.svg
odoo/addons/website_snippet_barcode/static/description/snippet_icon.png
odoo/addons/website_snippet_barcode/static/src/js/website_snippet_barcode.editor.js
odoo/addons/website_snippet_barcode/static/src/js/website_snippet_barcode.js
odoo/addons/website_snippet_barcode/static/tests/js/website_snippet_barcode.editor.tour.js
odoo/addons/website_snippet_barcode/templates/assets.xml
odoo/addons/website_snippet_barcode/templates/snippet_template.xml
odoo/addons/website_snippet_barcode/tests/__init__.py
odoo/addons/website_snippet_barcode/tests/test_ui.py
odoo10_addon_website_snippet_barcode-10.0.1.0.0.dist-info/DESCRIPTION.rst
odoo10_addon_website_snippet_barcode-10.0.1.0.0.dist-info/METADATA
odoo10_addon_website_snippet_barcode-10.0.1.0.0.dist-info/RECORD
odoo10_addon_website_snippet_barcode-10.0.1.0.0.dist-info/WHEEL
odoo10_addon_website_snippet_barcode-10.0.1.0.0.dist-info/metadata.json
odoo10_addon_website_snippet_barcode-10.0.1.0.0.dist-info/namespace_packages.txt
odoo10_addon_website_snippet_barcode-10.0.1.0.0.dist-info/top_level.txt
